spade_bokeh/__init__.py
spade_bokeh/spade_bokeh.py
spade_bokeh-0.2.1.dist-info/AUTHORS.rst
spade_bokeh-0.2.1.dist-info/LICENSE
spade_bokeh-0.2.1.dist-info/METADATA
spade_bokeh-0.2.1.dist-info/WHEEL
spade_bokeh-0.2.1.dist-info/top_level.txt
spade_bokeh-0.2.1.dist-info/RECORD
