Metadata-Version: 2.1
Name: spade-bokeh
Version: 0.2.1
Summary: Bokeh server for SPADE agents that integrates with agents web service.
Home-page: https://github.com/javipalanca/spade_bokeh
Author: Javi Palanca
Author-email: jpalanca@gmail.com
License: MIT license
Keywords: spade_bokeh
Classifier: Development Status :: 2 - Pre-Alpha
Classifier: Intended Audience :: Developers
Classifier: License :: OSI Approved :: MIT License
Classifier: Natural Language :: English
Classifier: Programming Language :: Python :: 3.8
Classifier: Programming Language :: Python :: 3.9
Classifier: Programming Language :: Python :: 3.10
License-File: LICENSE
License-File: AUTHORS.rst
Requires-Dist: spade (>=3.3.0)
Requires-Dist: tornado (==6.3.2)
Requires-Dist: bokeh (==3.1.1)
